tefs/__init__.py
tefs/core.py
tefs/estimation.py
tefs/metrics.py
tefs/types.py
tefs-1.0.0.dist-info/LICENSE
tefs-1.0.0.dist-info/METADATA
tefs-1.0.0.dist-info/WHEEL
tefs-1.0.0.dist-info/top_level.txt
tefs-1.0.0.dist-info/RECORD
