Metadata-Version: 2.1
Name: tefs
Version: 1.0.0
Summary: Causal feature selection for time series data using transfer entropy
Author-email: Teo Bucci <teobucci8@gmail.com>, Paolo Bonetti <paolo.bonetti@polimi.it>
License: MIT License
Project-URL: Homepage, https://github.com/PaoloBonettiPolimi/tefs
Project-URL: Documentation, https://PaoloBonettiPolimi.github.io/tefs/
Project-URL: Repository, https://github.com/PaoloBonettiPolimi/tefs
Keywords: tefs,transfer entropy,feature selection,causality,time series
Classifier: Programming Language :: Python :: 3
Classifier: License :: OSI Approved :: MIT License
Classifier: Operating System :: OS Independent
Requires-Python: >=3.9
License-File: LICENSE
Requires-Dist: numpy
Requires-Dist: pandas
Requires-Dist: matplotlib
Requires-Dist: scipy
Requires-Dist: seaborn
Requires-Dist: scikit-learn
